setup.py
test/test_briefings.py
test/test_conference.py
test/test_readme_examples.py
whtranscripts/__init__.py
whtranscripts/briefing.py
whtranscripts/conference.py
whtranscripts/download.py
whtranscripts/fixes.py
whtranscripts/passage.py
whtranscripts/patterns.py
whtranscripts/transcript.py
whtranscripts.egg-info/PKG-INFO
whtranscripts.egg-info/SOURCES.txt
whtranscripts.egg-info/dependency_links.txt
whtranscripts.egg-info/entry_points.txt
whtranscripts.egg-info/namespace_packages.txt
whtranscripts.egg-info/not-zip-safe
whtranscripts.egg-info/requires.txt
whtranscripts.egg-info/top_level.txt