Metadata-Version: 1.1
Name: whtranscripts
Version: 0.1.0
Summary: whtranscripts helps you fetch and parse transcripts from the American Presidency Project's press-briefing and presidential-news-conference transcripts.
Home-page: http://github.com/buzzfeednews/whtranscripts/
Author: John Templon
Author-email: john.templon@buzzfeed.com
License: MIT
Download-URL: https://github.com/BuzzFeedNews/whtranscripts/tarball/0.1
Keywords: white house news conferences press briefings american presidency project
Platform: UNKNOWN
Classifier: Development Status :: 3 - Alpha
Classifier: Intended Audience :: Developers
Classifier: License :: OSI Approved :: MIT License
Classifier: Operating System :: OS Independent
Classifier: Programming Language :: Python :: 2.7
Classifier: Programming Language :: Python :: 3.3
Classifier: Programming Language :: Python :: 3.5
